nlp_helper/__init__.py
nlp_helper/nlp.py
nlp_helper-0.0.6.dist-info/licenses/LICENSE
nlp_helper-0.0.6.dist-info/METADATA
nlp_helper-0.0.6.dist-info/WHEEL
nlp_helper-0.0.6.dist-info/top_level.txt
nlp_helper-0.0.6.dist-info/RECORD
